[
    {
        "title": "tormenta",
        "category": "Pop Culture",
        "badgeColor": "pink",
        "description": "Spike in daily searches triggered by public curiosity. Search queries highlight interest in: .",
        "growth": "+2000+",
        "growthNumeric": 2000,
        "platform": "Google Search",
        "volume": "2000+ queries",
        "sentiment": "Massive Focus",
        "trendDuration": "Exploding",
        "history": [
            173,
            392,
            534,
            1204,
            1160,
            1754,
            2000
        ],
        "id": "1",
        "hero": true
    },
    {
        "title": "weather san antonio",
        "category": "Pop Culture",
        "badgeColor": "pink",
        "description": "Spike in daily searches triggered by public curiosity. Search queries highlight interest in: .",
        "growth": "+2000+",
        "growthNumeric": 2000,
        "platform": "Google Search",
        "volume": "2000+ queries",
        "sentiment": "Curiosity Spike",
        "trendDuration": "Stable",
        "history": [
            177,
            390,
            574,
            874,
            1381,
            1830,
            2000
        ],
        "id": "2",
        "hero": false
    },
    {
        "title": "s janaki",
        "category": "Pop Culture",
        "badgeColor": "pink",
        "description": "Spike in daily searches triggered by public curiosity. Search queries highlight interest in: .",
        "growth": "+1000+",
        "growthNumeric": 1000,
        "platform": "Google Search",
        "volume": "1000+ queries",
        "sentiment": "Rising Interest",
        "trendDuration": "Rising",
        "history": [
            73,
            191,
            265,
            438,
            817,
            918,
            1000
        ],
        "id": "3",
        "hero": false
    },
    {
        "title": "houston weather",
        "category": "Tech & AI",
        "badgeColor": "purple",
        "description": "Spike in daily searches triggered by public curiosity. Search queries highlight interest in: .",
        "growth": "+1000+",
        "growthNumeric": 1000,
        "platform": "Google Search",
        "volume": "1000+ queries",
        "sentiment": "Curiosity Spike",
        "trendDuration": "Stable",
        "history": [
            76,
            177,
            314,
            443,
            585,
            920,
            1000
        ],
        "id": "4",
        "hero": false
    },
    {
        "title": "today wordle answers",
        "category": "Pop Culture",
        "badgeColor": "pink",
        "description": "Spike in daily searches triggered by public curiosity. Search queries highlight interest in: .",
        "growth": "+500+",
        "growthNumeric": 500,
        "platform": "Google Search",
        "volume": "500+ queries",
        "sentiment": "Massive Focus",
        "trendDuration": "Rising",
        "history": [
            36,
            96,
            167,
            243,
            339,
            432,
            500
        ],
        "id": "5",
        "hero": false
    },
    {
        "title": "billie jean king",
        "category": "Pop Culture",
        "badgeColor": "pink",
        "description": "Spike in daily searches triggered by public curiosity. Search queries highlight interest in: .",
        "growth": "+500+",
        "growthNumeric": 500,
        "platform": "Google Search",
        "volume": "500+ queries",
        "sentiment": "Rising Interest",
        "trendDuration": "Rising",
        "history": [
            46,
            76,
            132,
            276,
            363,
            414,
            500
        ],
        "id": "6",
        "hero": false
    },
    {
        "title": "maria sharapova",
        "category": "Pop Culture",
        "badgeColor": "pink",
        "description": "Spike in daily searches triggered by public curiosity. Search queries highlight interest in: .",
        "growth": "+500+",
        "growthNumeric": 500,
        "platform": "Google Search",
        "volume": "500+ queries",
        "sentiment": "Rising Interest",
        "trendDuration": "Stable",
        "history": [
            42,
            79,
            174,
            246,
            290,
            426,
            500
        ],
        "id": "7",
        "hero": false
    },
    {
        "title": "martina navratilova",
        "category": "Pop Culture",
        "badgeColor": "pink",
        "description": "Spike in daily searches triggered by public curiosity. Search queries highlight interest in: .",
        "growth": "+500+",
        "growthNumeric": 500,
        "platform": "Google Search",
        "volume": "500+ queries",
        "sentiment": "Curiosity Spike",
        "trendDuration": "Stable",
        "history": [
            47,
            100,
            176,
            258,
            380,
            481,
            500
        ],
        "id": "8",
        "hero": false
    }
]