[
    {
        "title": "jordan pickford",
        "category": "Pop Culture",
        "badgeColor": "pink",
        "description": "Spike in daily searches triggered by public curiosity. Search queries highlight interest in: .",
        "growth": "+5000+",
        "growthNumeric": 5000,
        "platform": "Google Search",
        "volume": "5000+ queries",
        "sentiment": "Massive Focus",
        "trendDuration": "Exploding",
        "history": [
            464,
            997,
            1773,
            2435,
            4171,
            4098,
            5000
        ],
        "id": "1",
        "hero": true
    },
    {
        "title": "kaka",
        "category": "Pop Culture",
        "badgeColor": "pink",
        "description": "Spike in daily searches triggered by public curiosity. Search queries highlight interest in: .",
        "growth": "+2000+",
        "growthNumeric": 2000,
        "platform": "Google Search",
        "volume": "2000+ queries",
        "sentiment": "Massive Focus",
        "trendDuration": "Rising",
        "history": [
            172,
            373,
            584,
            1115,
            1263,
            1701,
            2000
        ],
        "id": "2",
        "hero": false
    },
    {
        "title": "oscar bobb",
        "category": "Pop Culture",
        "badgeColor": "pink",
        "description": "Spike in daily searches triggered by public curiosity. Search queries highlight interest in: .",
        "growth": "+2000+",
        "growthNumeric": 2000,
        "platform": "Google Search",
        "volume": "2000+ queries",
        "sentiment": "Rising Interest",
        "trendDuration": "Rising",
        "history": [
            174,
            305,
            721,
            1039,
            1357,
            1709,
            2000
        ],
        "id": "3",
        "hero": false
    },
    {
        "title": "fifa president",
        "category": "Gaming",
        "badgeColor": "cyan",
        "description": "Spike in daily searches triggered by public curiosity. Search queries highlight interest in: .",
        "growth": "+2000+",
        "growthNumeric": 2000,
        "platform": "Google Search",
        "volume": "2000+ queries",
        "sentiment": "Rising Interest",
        "trendDuration": "Rising",
        "history": [
            171,
            388,
            697,
            1003,
            1494,
            1797,
            2000
        ],
        "id": "4",
        "hero": false
    },
    {
        "title": "infantino",
        "category": "Pop Culture",
        "badgeColor": "pink",
        "description": "Spike in daily searches triggered by public curiosity. Search queries highlight interest in: .",
        "growth": "+1000+",
        "growthNumeric": 1000,
        "platform": "Google Search",
        "volume": "1000+ queries",
        "sentiment": "Curiosity Spike",
        "trendDuration": "Stable",
        "history": [
            88,
            166,
            280,
            522,
            562,
            912,
            1000
        ],
        "id": "5",
        "hero": false
    },
    {
        "title": "what time does paddy pimblett fight",
        "category": "Pop Culture",
        "badgeColor": "pink",
        "description": "Spike in daily searches triggered by public curiosity. Search queries highlight interest in: .",
        "growth": "+1000+",
        "growthNumeric": 1000,
        "platform": "Google Search",
        "volume": "1000+ queries",
        "sentiment": "Curiosity Spike",
        "trendDuration": "Stable",
        "history": [
            92,
            144,
            333,
            594,
            707,
            796,
            1000
        ],
        "id": "6",
        "hero": false
    },
    {
        "title": "ronaldo nazario",
        "category": "Gaming",
        "badgeColor": "cyan",
        "description": "Spike in daily searches triggered by public curiosity. Search queries highlight interest in: .",
        "growth": "+500+",
        "growthNumeric": 500,
        "platform": "Google Search",
        "volume": "500+ queries",
        "sentiment": "Rising Interest",
        "trendDuration": "Stable",
        "history": [
            43,
            95,
            180,
            219,
            337,
            451,
            500
        ],
        "id": "7",
        "hero": false
    },
    {
        "title": "peyton bonds",
        "category": "Pop Culture",
        "badgeColor": "pink",
        "description": "Spike in daily searches triggered by public curiosity. Search queries highlight interest in: .",
        "growth": "+500+",
        "growthNumeric": 500,
        "platform": "Google Search",
        "volume": "500+ queries",
        "sentiment": "Curiosity Spike",
        "trendDuration": "Stable",
        "history": [
            33,
            91,
            142,
            265,
            313,
            396,
            500
        ],
        "id": "8",
        "hero": false
    }
]