[
    {
        "title": "marshall manning freshman quarterback",
        "category": "Pop Culture",
        "badgeColor": "pink",
        "description": "Spike in daily searches triggered by public curiosity. Search queries highlight interest in: .",
        "growth": "+2000+",
        "growthNumeric": 2000,
        "platform": "Google Search",
        "volume": "2000+ queries",
        "sentiment": "Rising Interest",
        "trendDuration": "Rising",
        "history": [
            174,
            420,
            544,
            860,
            1330,
            1688,
            2000
        ],
        "id": "1",
        "hero": true
    },
    {
        "title": "radar",
        "category": "Pop Culture",
        "badgeColor": "pink",
        "description": "Spike in daily searches triggered by public curiosity. Search queries highlight interest in: .",
        "growth": "+2000+",
        "growthNumeric": 2000,
        "platform": "Google Search",
        "volume": "2000+ queries",
        "sentiment": "Curiosity Spike",
        "trendDuration": "Stable",
        "history": [
            163,
            347,
            744,
            908,
            1368,
            1723,
            2000
        ],
        "id": "2",
        "hero": false
    },
    {
        "title": "tour de france standings",
        "category": "Pop Culture",
        "badgeColor": "pink",
        "description": "Spike in daily searches triggered by public curiosity. Search queries highlight interest in: .",
        "growth": "+1000+",
        "growthNumeric": 1000,
        "platform": "Google Search",
        "volume": "1000+ queries",
        "sentiment": "Massive Focus",
        "trendDuration": "Rising",
        "history": [
            93,
            214,
            310,
            458,
            594,
            891,
            1000
        ],
        "id": "3",
        "hero": false
    },
    {
        "title": "kyle bylin jeremy morrison lawsuit",
        "category": "Pop Culture",
        "badgeColor": "pink",
        "description": "Spike in daily searches triggered by public curiosity. Search queries highlight interest in: .",
        "growth": "+1000+",
        "growthNumeric": 1000,
        "platform": "Google Search",
        "volume": "1000+ queries",
        "sentiment": "Rising Interest",
        "trendDuration": "Rising",
        "history": [
            93,
            179,
            309,
            520,
            607,
            953,
            1000
        ],
        "id": "4",
        "hero": false
    },
    {
        "title": "tornado warning rochester ny",
        "category": "Pop Culture",
        "badgeColor": "pink",
        "description": "Spike in daily searches triggered by public curiosity. Search queries highlight interest in: .",
        "growth": "+1000+",
        "growthNumeric": 1000,
        "platform": "Google Search",
        "volume": "1000+ queries",
        "sentiment": "Curiosity Spike",
        "trendDuration": "Stable",
        "history": [
            89,
            151,
            320,
            595,
            698,
            947,
            1000
        ],
        "id": "5",
        "hero": false
    },
    {
        "title": "anna melisano",
        "category": "Pop Culture",
        "badgeColor": "pink",
        "description": "Spike in daily searches triggered by public curiosity. Search queries highlight interest in: .",
        "growth": "+500+",
        "growthNumeric": 500,
        "platform": "Google Search",
        "volume": "500+ queries",
        "sentiment": "Massive Focus",
        "trendDuration": "Exploding",
        "history": [
            44,
            75,
            154,
            272,
            364,
            440,
            500
        ],
        "id": "6",
        "hero": false
    },
    {
        "title": "christian leroy duncan",
        "category": "Pop Culture",
        "badgeColor": "pink",
        "description": "Spike in daily searches triggered by public curiosity. Search queries highlight interest in: .",
        "growth": "+500+",
        "growthNumeric": 500,
        "platform": "Google Search",
        "volume": "500+ queries",
        "sentiment": "Rising Interest",
        "trendDuration": "Stable",
        "history": [
            32,
            94,
            182,
            266,
            304,
            441,
            500
        ],
        "id": "7",
        "hero": false
    },
    {
        "title": "david malukas",
        "category": "Pop Culture",
        "badgeColor": "pink",
        "description": "Spike in daily searches triggered by public curiosity. Search queries highlight interest in: .",
        "growth": "+500+",
        "growthNumeric": 500,
        "platform": "Google Search",
        "volume": "500+ queries",
        "sentiment": "Curiosity Spike",
        "trendDuration": "Stable",
        "history": [
            33,
            97,
            168,
            271,
            392,
            400,
            500
        ],
        "id": "8",
        "hero": false
    }
]